vredis/__init__.py
vredis/cmdline.py
vredis/common.py
vredis/defaults.py
vredis/error.py
vredis/order.py
vredis/pipeline.py
vredis/sender.py
vredis/utils.py
vredis/worker.py
vredis.py-1.2.5.dist-info/LICENSE
vredis.py-1.2.5.dist-info/METADATA
vredis.py-1.2.5.dist-info/WHEEL
vredis.py-1.2.5.dist-info/entry_points.txt
vredis.py-1.2.5.dist-info/top_level.txt
vredis.py-1.2.5.dist-info/RECORD
