Metadata-Version: 2.1
Name: vredis.py
Version: 1.2.5
Summary: Distributed script crawler framework.
Home-page: https://github.com/cilame/vredis
Author: cilame
Author-email: opaquism@hotmail.com
License: MIT
Platform: UNKNOWN
Classifier: Environment :: Web Environment
Classifier: Intended Audience :: Developers
Classifier: Operating System :: OS Independent
Requires-Python: >=3.6
Requires-Dist: redis
